{
  "name": "josephluck/helix",
  "version": "0.1.4",
  "libraries": {
    "xv": "^1.1.25"
  },
  "title": "Helix",
  "branch": "master",
  "style": {
    "name": "Brutalist",
    "componentSet": {
      "nav": "nav/BasicNav",
      "header": "header/BasicHeader",
      "article": "article/MarkdownArticle",
      "footer": "footer/BasicFooter"
    },
    "fontFamily": "Consolas, \"Liberation Mono\", Menlo, Courier, monospace",
    "heading": {},
    "typeScale": [
      48,
      32,
      20,
      18,
      16,
      14,
      12
    ],
    "layout": {
      "maxWidth": 1024,
      "fluid": true
    },
    "colors": {
      "text": "#333",
      "background": "#fff",
      "primary": "#666",
      "secondary": "#888",
      "highlight": "#1f80ff",
      "muted": "#f6f6f6",
      "border": "#eee"
    }
  },
  "content": [
    {
      "component": "nav",
      "links": [
        {
          "href": "https://github.com/josephluck/helix",
          "text": "GitHub"
        },
        {
          "href": "https://npmjs.com/package/helix-js",
          "text": "npm"
        }
      ]
    },
    {
      "component": "header",
      "heading": "helix",
      "subhead": "Yet another front-end framework",
      "children": [
        {
          "component": "ui/TweetButton",
          "text": "helix: Yet another front-end framework",
          "url": null
        },
        {
          "component": "ui/GithubButton",
          "user": "josephluck",
          "repo": "helix"
        }
      ],
      "text": "v1.4.1"
    },
    {
      "component": "article",
      "metadata": {
        "source": "github.readme"
      },
      "html": "\n<p>Helix is a batteries included framework for building interactive &quot;single-page&quot; applications. Helix applications are written in JavaScript and typically run in a web browser.</p>\n<p>Helix provides a functional approach to building rich front-end applications and works well with Typescript.</p>\n<p>Helix &amp; Twine were created by Joseph Luck and the good folks at Goodlord.</p>\n<h1>Installation</h1>\n<p>Helix comes in a few flavours.</p>\n<h3>Vanilla</h3>\n<pre>npm install helix-js</pre><h3>Helix with React</h3>\n<pre>npm install helix-react</pre><h3>Helix with Yo-yo</h3>\n<pre>npm install helix-yo-yo</pre><h3>Helix with Vue</h3>\n<pre>npm install helix-vue</pre><h3>State logger</h3>\n<pre>npm install twine-log</pre>"
    },
    {
      "component": "footer",
      "links": [
        {
          "href": "https://github.com/josephluck/helix",
          "text": "GitHub"
        },
        {
          "href": "https://github.com/josephluck",
          "text": "josephluck"
        }
      ]
    }
  ]
}